arubafi/__init__.py
arubafi/_version.py
arubafi/airwave.py
arubafi/mmclient.py
arubafi/tests/__init__.py
arubafi/tests/test_mmclient.py
arubafi-0.0.10.dist-info/LICENSE.md
arubafi-0.0.10.dist-info/METADATA
arubafi-0.0.10.dist-info/WHEEL
arubafi-0.0.10.dist-info/top_level.txt
arubafi-0.0.10.dist-info/RECORD
