Metadata-Version: 2.1
Name: arubafi
Version: 0.0.10
Summary: Aruba Networks API Python module for AirWave and Mobility Master
Home-page: UNKNOWN
Author: Primoz Marinsek
Author-email: primoz.marinsek@ocado.com
License: Apache-2.0
Platform: UNKNOWN
Requires-Dist: requests
Requires-Dist: logzero
Requires-Dist: xmltodict
